{
  "nome": "Bent Over Row con Manubri con Palme Rivolte all'Interno",
  "forza": "tirare",
  "livello": "principiante",
  "meccanica": "composta",
  "attrezzatura": "manubrio",
  "muscoliPrimari": [
    "dorso medio"
  ],
  "muscoliSecondari": [
    "bicipiti",
    "lats"
  ],
  "istruzioni": [
    "Con un manubrio in ogni mano (palme rivolte l'una verso l'altra), piega le ginocchia leggermente e porta il tuo busto in avanti, piegandoti in vita e mantenendo la schiena dritta fino a quando non è quasi parallela al pavimento. Suggerimento: Assicurati di tenere la testa alta. I manubri dovrebbero pendere direttamente davanti a te come le braccia pendono perpendicolarmente al pavimento e il tuo busto. Questa è la tua posizione di partenza.",
    "Mentre mantieni il busto fermo, solleva i manubri ai tuoi lati mentre espiri, stringendo le scapole insieme. Nella posizione contratta in alto, stringi i muscoli posteriori e tieni premuto per un secondo.",
    "Abbassa lentamente il peso nuovamente alla posizione di partenza mentre inspiri.",
    "Ripeti per il numero consigliato di ripetizioni."
  ],
  "categoria": "forza",
  "immagini": [
    "Bent_Over_Two-Dumbbell_Row_With_Palms_In/0.jpg",
    "Bent_Over_Two-Dumbbell_Row_With_Palms_In/1.jpg"
  ],
  "id": "Bent_Over_Two-Dumbbell_Row_With_Palms_In",
  "images": [
    "Bent_Over_Two-Dumbbell_Row_With_Palms_In/0.jpg",
    "Bent_Over_Two-Dumbbell_Row_With_Palms_In/1.jpg"
  ]
}