{
  "nome": "Lateral Raise - Con Bande",
  "forza": "spinta",
  "livello": "principiante",
  "meccanismo": "isolamento",
  "attrezzatura": "bande",
  "muscoliPrimari": [
    "spalle"
  ],
  "muscoliSecondari": [],
  "istruzioni": [
    "Per iniziare, mettiti in piedi su una banda per esercizi in modo che la tensione inizi a lunghezza del braccio. Afferra le maniglie utilizzando una presa pronata (palme rivolte verso le cosce) che è leggermente inferiore alla larghezza delle spalle. Le maniglie dovrebbero poggiare sui lati delle tue cosce. Le tue braccia dovrebbero essere estese con una leggera piega ai gomiti e la tua schiena dovrebbe essere dritta. Questa sarà la tua posizione di partenza.",
    "Usa le spalle laterali per sollevare le maniglie lateralmente mentre espiri. Continua a sollevare le maniglie finché non sono leggermente sopra il parallelo. Suggerimento: mentre sollevi le maniglie, inclina leggermente la mano come se stessi versando dell'acqua e mantieni le braccia estese. Inoltre, mantieni il torace fermo e mettiti in pausa per un secondo all'apice del movimento.",
    "Abbassa lentamente le maniglie alla posizione di partenza. Inspira mentre esegui questa parte del movimento.",
    "Ripeti per il numero di ripetizioni consigliato."
  ],
  "categoria": "forza",
  "immagini": [
    "Lateral_Raise_-_With_Bands/0.jpg",
    "Lateral_Raise_-_With_Bands/1.jpg"
  ],
  "id": "Lateral_Raise_-_With_Bands",
  "images": [
    "Lateral_Raise_-_With_Bands/0.jpg",
    "Lateral_Raise_-_With_Bands/1.jpg"
  ]
}